desdeo_tools/interaction/__init__.py
desdeo_tools/interaction/request.py
desdeo_tools/interaction/validators.py
desdeo_tools/maps/__init__.py
desdeo_tools/maps/preference_incorporated_space_RP.py
desdeo_tools/scalarization/ASF.py
desdeo_tools/scalarization/EpsilonConstraintMethod.py
desdeo_tools/scalarization/GLIDE_II.py
desdeo_tools/scalarization/MOEADSF.py
desdeo_tools/scalarization/Scalarizer.py
desdeo_tools/scalarization/__init__.py
desdeo_tools/solver/ScalarSolver.py
desdeo_tools/solver/__init__.py
desdeo_tools/utilities/__init__.py
desdeo_tools/utilities/distance_to_reference_point.py
desdeo_tools/utilities/fast_non_dominated_sorting.py
desdeo_tools/utilities/frozen.py
desdeo_tools/utilities/lattice_generators.py
desdeo_tools/utilities/pmod.py
desdeo_tools/utilities/polytopes.py
desdeo_tools/utilities/preference_converters.py
desdeo_tools/utilities/quality_indicator.py
desdeo_tools-1.9.0.dist-info/LICENSE
desdeo_tools-1.9.0.dist-info/METADATA
desdeo_tools-1.9.0.dist-info/WHEEL
desdeo_tools-1.9.0.dist-info/RECORD
