Metadata-Version: 2.1
Name: desdeo-tools
Version: 1.9.0
Summary: Generic tools and design language used in the DESDEO framework
License: MIT
Author: Bhupinder Saini
Requires-Python: >=3.11,<3.12
Classifier: License :: OSI Approved :: MIT License
Classifier: Programming Language :: Python :: 3
Classifier: Programming Language :: Python :: 3.11
Provides-Extra: mixed-integer-solver
Requires-Dist: hvwfg (>=1.0.2,<2.0.0)
Requires-Dist: numba (>=0.58,<0.59)
Requires-Dist: numpy (>=1.17,<2.0)
Requires-Dist: pandas (>=1.0,<2.0)
Requires-Dist: scipy (>=1.2,<2.0)
